mimic_user_agent/__init__.py
mimic_user_agent/mimicUserAgent.py
mimic_user_agent-0.0.5.dist-info/LICENSE
mimic_user_agent-0.0.5.dist-info/METADATA
mimic_user_agent-0.0.5.dist-info/WHEEL
mimic_user_agent-0.0.5.dist-info/top_level.txt
mimic_user_agent-0.0.5.dist-info/RECORD
