Metadata-Version: 2.1
Name: mimic_user_agent
Version: 0.0.5
Summary: simple user-agent generator.
Author-email: kurotom <author@example.com>
Project-URL: Homepage, https://github.com/kurotom/mimic_user_agent
Project-URL: Bug Tracker, https://github.com/kurotom/mimic_user_agent/issues
Classifier: Programming Language :: Python :: 3
Classifier: License :: OSI Approved :: MIT License
Classifier: Operating System :: OS Independent
Requires-Python: >=3.7
License-File: LICENSE
